lrasm/__init__.py
lrasm/homoscedasticity_tst.py
lrasm/multicollinearity_tst.py
lrasm/normality_tst.py
lrasm-0.1.3.dist-info/LICENSE
lrasm-0.1.3.dist-info/WHEEL
lrasm-0.1.3.dist-info/METADATA
lrasm-0.1.3.dist-info/RECORD
