Metadata-Version: 2.1
Name: lrasm
Version: 0.1.3
Summary: A package containing functions to test linearity assumptions for linear regression performed on single or multiple linear regression for a specified dataset
License: MIT
Author: Yair Guterman, Hatef Rahmani, Song Bo Andy Yang 
Requires-Python: >=3.9,<3.11
Classifier: License :: OSI Approved :: MIT License
Classifier: Programming Language :: Python :: 3
Classifier: Programming Language :: Python :: 3.10
Classifier: Programming Language :: Python :: 3.9
Requires-Dist: matplotlib (>=3.5.1,<4.0.0)
Requires-Dist: numpy (>=1.22.1,<2.0.0)
Requires-Dist: pandas (>=1.3.5,<2.0.0)
Requires-Dist: scipy (>=1.7.3,<2.0.0)
Requires-Dist: sklearn (>=0.0,<0.1)
Requires-Dist: statsmodels (>=0.13.1,<0.14.0)
